Metadata-Version: 2.1
Name: zikasort
Version: 0.0.6
Summary: Sorter for files.
Home-page: UNKNOWN
Author: Zika Walter
Author-email: example@example.com
License: APACHE
Keywords: sorter
Platform: UNKNOWN
Classifier: Development Status :: 5 - Production/Stable
Classifier: Intended Audience :: End Users/Desktop
Classifier: Operating System :: Microsoft :: Windows :: Windows 10
Classifier: License :: OSI Approved :: Apache Software License
Classifier: Programming Language :: Python :: 3
License-File: LICENCE.txt
